README.md
setup.py
smartninja_sql/__init__.py
smartninja_sql/sqlite.py
smartninja_sql.egg-info/PKG-INFO
smartninja_sql.egg-info/SOURCES.txt
smartninja_sql.egg-info/dependency_links.txt
smartninja_sql.egg-info/requires.txt
smartninja_sql.egg-info/top_level.txt