Metadata-Version: 2.1
Name: smartninja-sql
Version: 0.3
Summary: SmartNinja SQL - a simple SQLite wrapper.
Home-page: https://github.com/smartninja/smartninja-sql
Author: Matej Ramuta
Author-email: matej.ramuta@gmail.com
License: MIT
Platform: UNKNOWN
Classifier: Programming Language :: Python :: 3
Classifier: License :: OSI Approved :: MIT License
Classifier: Operating System :: OS Independent
